ynab_amazon_categorizer/__init__.py
ynab_amazon_categorizer/__main__.py
ynab_amazon_categorizer/_version.py
ynab_amazon_categorizer/amazon_parser.py
ynab_amazon_categorizer/cli.py
ynab_amazon_categorizer/config.py
ynab_amazon_categorizer/exceptions.py
ynab_amazon_categorizer/memo_generator.py
ynab_amazon_categorizer/transaction_matcher.py
ynab_amazon_categorizer/ynab_client.py
ynab_amazon_categorizer-2.1.2.dist-info/licenses/LICENSE
ynab_amazon_categorizer-2.1.2.dist-info/METADATA
ynab_amazon_categorizer-2.1.2.dist-info/WHEEL
ynab_amazon_categorizer-2.1.2.dist-info/entry_points.txt
ynab_amazon_categorizer-2.1.2.dist-info/top_level.txt
ynab_amazon_categorizer-2.1.2.dist-info/RECORD
