Metadata-Version: 2.4
Name: ynab-amazon-categorizer
Version: 2.1.2
Summary: Automatically categorize Amazon transactions in YNAB with rich item information
Author: dizzlkheinz
License: GPL-3.0
Project-URL: Homepage, https://github.com/dizzlkheinz/ynab-amazon-categorizer
Project-URL: Repository, https://github.com/dizzlkheinz/ynab-amazon-categorizer
Project-URL: Issues, https://github.com/dizzlkheinz/ynab-amazon-categorizer/issues
Keywords: ynab,amazon,budgeting,finance,automation
Classifier: Development Status :: 4 - Beta
Classifier: Environment :: Console
Classifier: Intended Audience :: End Users/Desktop
Classifier: License :: OSI Approved :: GNU General Public License v3 (GPLv3)
Classifier: Operating System :: OS Independent
Classifier: Programming Language :: Python :: 3
Classifier: Programming Language :: Python :: 3.9
Classifier: Programming Language :: Python :: 3.10
Classifier: Programming Language :: Python :: 3.11
Classifier: Programming Language :: Python :: 3.12
Classifier: Programming Language :: Python :: 3.13
Classifier: Topic :: Office/Business :: Financial :: Accounting
Classifier: Topic :: Utilities
Requires-Python: >=3.9
License-File: LICENSE
Requires-Dist: requests>=2.25.0
Requires-Dist: prompt_toolkit>=3.0.0
Requires-Dist: pydantic>=2.0.0
Requires-Dist: python-dotenv>=1.0.0
Provides-Extra: dev
Requires-Dist: pytest>=7.0.0; extra == "dev"
Requires-Dist: pytest-cov>=4.0.0; extra == "dev"
Requires-Dist: black>=22.0.0; extra == "dev"
Requires-Dist: ruff>=0.1.0; extra == "dev"
Requires-Dist: mypy>=1.0.0; extra == "dev"
Requires-Dist: pre-commit>=3.0.0; extra == "dev"
Dynamic: license-file
